obscraper/__init__.py
obscraper/__main__.py
obscraper/_assemble.py
obscraper/_download.py
obscraper/_exceptions.py
obscraper/_extract_post.py
obscraper/_fetch.py
obscraper/_post.py
obscraper/_scrape.py
obscraper/_serialize.py
obscraper/_tidy.py
obscraper/_utils.py
obscraper/_version.py
obscraper-0.8.3.dist-info/METADATA
obscraper-0.8.3.dist-info/WHEEL
obscraper-0.8.3.dist-info/entry_points.txt
obscraper-0.8.3.dist-info/licenses/LICENSE
obscraper-0.8.3.dist-info/RECORD
