Metadata-Version: 2.1
Name: obscraper
Version: 0.8.3
Summary: obscraper: scrape posts from the overcomingbias blog
Project-URL: changelog, https://obscraper.readthedocs.io/en/stable/changelog.html
Project-URL: repository, https://github.com/chris-mcdo/obscraper
Project-URL: issues, https://github.com/chris-mcdo/obscraper/issues
Author-email: Christopher McDonald <cmcdonal33@gmail.com>
License: MIT License
License-File: LICENSE
Keywords: api,bs4,overcomingbias
Classifier: Development Status :: 4 - Beta
Classifier: Intended Audience :: Developers
Classifier: License :: OSI Approved :: MIT License
Classifier: Operating System :: MacOS :: MacOS X
Classifier: Operating System :: Microsoft :: Windows
Classifier: Operating System :: POSIX
Classifier: Programming Language :: Python :: 3
Classifier: Programming Language :: Python :: 3 :: Only
Classifier: Programming Language :: Python :: 3.8
Classifier: Programming Language :: Python :: 3.9
Classifier: Programming Language :: Python :: 3.10
Classifier: Programming Language :: Python :: 3.11
Classifier: Topic :: Internet
Classifier: Topic :: Internet :: WWW/HTTP :: Indexing/Search
Requires-Python: >=3.8
Requires-Dist: beautifulsoup4>=4.8
Requires-Dist: cachetools>=4.2
Requires-Dist: httpx[http2]>=0.20.0
Requires-Dist: lxml>=3
Requires-Dist: python-dateutil>=2.7
Requires-Dist: pytz
Requires-Dist: trio>=0.19.0
Provides-Extra: test
Requires-Dist: pytest; extra == 'test'
Requires-Dist: pytest-trio; extra == 'test'
